example_package_edubarse_attempt_3/__init__.py
example_package_edubarse_attempt_3/check.py
example_package_edubarse_attempt_3/question2.py
example_package_edubarse_attempt_3/question2_modified.py
example_package_edubarse_attempt_3-0.0.1.dist-info/LICENSE
example_package_edubarse_attempt_3-0.0.1.dist-info/METADATA
example_package_edubarse_attempt_3-0.0.1.dist-info/WHEEL
example_package_edubarse_attempt_3-0.0.1.dist-info/top_level.txt
example_package_edubarse_attempt_3-0.0.1.dist-info/RECORD
